README.md
setup.py
tess_zap.egg-info/PKG-INFO
tess_zap.egg-info/SOURCES.txt
tess_zap.egg-info/dependency_links.txt
tess_zap.egg-info/not-zip-safe
tess_zap.egg-info/requires.txt
tess_zap.egg-info/top_level.txt
tesszap/__init__.py
tesszap/imports.py
tesszap/models.py
tesszap/noise.py
tesszap/strategies.py
tesszap/tess.py
tesszap/timeseries.py