Metadata-Version: 1.1
Name: tess-zap
Version: 0.0.2
Summary: Tool to simulate the effects of the TESS cosmic ray mitigation on light curves.
Home-page: https://github.com/zkbt/tess-zap
Author: Zach Berta-Thompson
Author-email: zach.bertathompson@colorado.edu
License: MIT
Platform: UNKNOWN
Classifier: Intended Audience :: Science/Research
Classifier: Programming Language :: Python
Classifier: Topic :: Scientific/Engineering :: Astronomy
